{"version": 0.6, "generator": "Overpass API 0.7.62.4 2390de5a", "osm3s": {"timestamp_osm_base": "2024-11-23T15:49:02Z", "copyright": "The data included in this document is from www.openstreetmap.org. The data is made available under ODbL."}, "elements": [{"type": "node", "id": 3233853952, "lat": 9.394006, "lon": 4.8411347}, {"type": "node", "id": 3233853953, "lat": 9.3943632, "lon": 4.842267}, {"type": "node", "id": 3233853954, "lat": 9.4017296, "lon": 4.8525691}, {"type": "node", "id": 3233853955, "lat": 9.4039644, "lon": 4.8587687}, {"type": "node", "id": 3233853956, "lat": 9.4303104, "lon": 4.881123}, {"type": "node", "id": 3233853957, "lat": 9.4357205, "lon": 4.8851766}, {"type": "node", "id": 3233853958, "lat": 9.4391852, "lon": 4.9043857}, {"type": "node", "id": 3233853959, "lat": 9.4397192, "lon": 4.8906608}, {"type": "node", "id": 3233853960, "lat": 9.4445075, "lon": 4.9189702}, {"type": "node", "id": 3233853961, "lat": 9.4450896, "lon": 4.9330489}, {"type": "node", "id": 3233853963, "lat": 9.4523123, "lon": 4.9438981}, {"type": "node", "id": 3233853964, "lat": 9.4526651, "lon": 4.9514688}, {"type": "node", "id": 3233853967, "lat": 9.4581466, "lon": 4.963515}, {"type": "node", "id": 3233854004, "lat": 9.4634257, "lon": 4.9666697}, {"type": "node", "id": 3233854010, "lat": 9.4641313, "lon": 4.9688157}, {"type": "node", "id": 3233854027, "lat": 9.4682473, "lon": 4.9718559}, {"type": "node", "id": 3233854031, "lat": 9.4714224, "lon": 4.9789496}, {"type": "node", "id": 3233854033, "lat": 9.472422, "lon": 4.9834801}, {"type": "node", "id": 3233854034, "lat": 9.4750091, "lon": 4.9854473}, {"type": "node", "id": 3233854035, "lat": 9.4754795, "lon": 4.9873549}, {"type": "node", "id": 3233854036, "lat": 9.4787134, "lon": 4.9897989}, {"type": "node", "id": 3233854037, "lat": 9.4795953, "lon": 4.9919449}, {"type": "node", "id": 3233854038, "lat": 9.4826528, "lon": 4.9927795}, {"type": "node", "id": 3233854040, "lat": 9.4848283, "lon": 4.9920045}, {"type": "node", "id": 3233854041, "lat": 9.4864746, "lon": 4.9928391}, {"type": "node", "id": 3233854042, "lat": 9.4878269, "lon": 4.9955812}, {"type": "node", "id": 3233854045, "lat": 9.4934712, "lon": 4.9999925}, {"type": "node", "id": 3233854048, "lat": 9.5012909, "lon": 5.0032711}, {"type": "node", "id": 3233854049, "lat": 9.5028195, "lon": 5.0055959}, {"type": "node", "id": 3233854051, "lat": 9.5095219, "lon": 5.0073247}, {"type": "node", "id": 3233854052, "lat": 9.5109329, "lon": 5.0089938}, {"type": "node", "id": 3233854053, "lat": 9.5133252, "lon": 5.0098103}, {"type": "node", "id": 3233854057, "lat": 9.5201631, "lon": 5.0175778}, {"type": "node", "id": 3233854059, "lat": 9.5241021, "lon": 5.018472}, {"type": "node", "id": 3233854061, "lat": 9.5268064, "lon": 5.0212737}, {"type": "node", "id": 3233854062, "lat": 9.5298634, "lon": 5.0217506}, {"type": "node", "id": 3233854063, "lat": 9.5312743, "lon": 5.0275926}, {"type": "node", "id": 3233854064, "lat": 9.5321553, "lon": 5.1167966}, {"type": "node", "id": 3233854065, "lat": 9.5326265, "lon": 5.0255658}, {"type": "node", "id": 3233854066, "lat": 9.533006, "lon": 5.1042886}, {"type": "node", "id": 3233854067, "lat": 9.5335164, "lon": 5.0935922}, {"type": "node", "id": 3233854069, "lat": 9.5348775, "lon": 5.1079979}, {"type": "node", "id": 3233854072, "lat": 9.5363237, "lon": 5.131116}, {"type": "node", "id": 3233854073, "lat": 9.5365065, "lon": 5.031825}, {"type": "node", "id": 3233854074, "lat": 9.5376234, "lon": 5.0351632}, {"type": "node", "id": 3233854075, "lat": 9.539131, "lon": 5.0865188}, {"type": "node", "id": 3233854077, "lat": 9.541327, "lon": 5.0387995}, {"type": "node", "id": 3233854078, "lat": 9.5416831, "lon": 5.1362917}, {"type": "node", "id": 3233854079, "lat": 9.5420913, "lon": 5.0419589}, {"type": "node", "id": 3233854081, "lat": 9.5443251, "lon": 5.0434492}, {"type": "node", "id": 3233854083, "lat": 9.5457663, "lon": 5.0785827}, {"type": "node", "id": 3233854084, "lat": 9.5460887, "lon": 5.0523313}, {"type": "node", "id": 3233854085, "lat": 9.5463618, "lon": 5.0701291}, {"type": "node", "id": 3233854088, "lat": 9.5499686, "lon": 5.0589482}, {"type": "node", "id": 3233854090, "lat": 9.5516359, "lon": 5.1398284}, {"type": "node", "id": 3233854091, "lat": 9.5522024, "lon": 5.0630613}, {"type": "node", "id": 3233854092, "lat": 9.5534223, "lon": 5.1444003}, {"type": "node", "id": 3233854094, "lat": 9.5549008, "lon": 5.0639652}, {"type": "node", "id": 3233854095, "lat": 9.5574873, "lon": 5.0668862}, {"type": "node", "id": 3233854097, "lat": 9.5626942, "lon": 5.1484545}, {"type": "node", "id": 3233854098, "lat": 9.5647764, "lon": 5.0681976}, {"type": "node", "id": 3233854101, "lat": 9.5684045, "lon": 5.1922642}, {"type": "node", "id": 3233854103, "lat": 9.5697654, "lon": 5.21659}, {"type": "node", "id": 3233854104, "lat": 9.5706901, "lon": 5.1569082}, {"type": "node", "id": 3233854106, "lat": 9.5713012, "lon": 5.0712974}, {"type": "node", "id": 3233854110, "lat": 9.5748691, "lon": 5.2322896}, {"type": "node", "id": 3233854113, "lat": 9.5764852, "lon": 5.2274589}, {"type": "node", "id": 3233854114, "lat": 9.577003, "lon": 5.0714762}, {"type": "node", "id": 3233854115, "lat": 9.5778462, "lon": 5.1837243}, {"type": "node", "id": 3233854118, "lat": 9.5787664, "lon": 5.0738011}, {"type": "node", "id": 3233854120, "lat": 9.580557, "lon": 5.1778697}, {"type": "node", "id": 3233854122, "lat": 9.5808232, "lon": 5.239363}, {"type": "node", "id": 3233854123, "lat": 9.5816738, "lon": 5.2447112}, {"type": "node", "id": 3233854129, "lat": 9.5859963, "lon": 5.0743972}, {"type": "node", "id": 3233854131, "lat": 9.5880531, "lon": 5.2504045}, {"type": "node", "id": 3233854133, "lat": 9.5892879, "lon": 5.076424}, {"type": "node", "id": 3233854151, "lat": 9.6028067, "lon": 5.073205}, {"type": "node", "id": 3233854164, "lat": 9.6167951, "lon": 5.0740991}, {"type": "node", "id": 3233854179, "lat": 9.62614, "lon": 5.0774374}, {"type": "node", "id": 3233854183, "lat": 9.6338391, "lon": 5.0776758}, {"type": "node", "id": 3233854187, "lat": 9.6372478, "lon": 5.0800007}, {"type": "node", "id": 3233854191, "lat": 9.6422432, "lon": 5.0811333}, {"type": "node", "id": 3233854192, "lat": 9.6439475, "lon": 5.0832197}, {"type": "node", "id": 3233854197, "lat": 9.6495056, "lon": 5.0832105}, {"type": "node", "id": 3233854200, "lat": 9.6561202, "lon": 5.0822956}, {"type": "node", "id": 3233854212, "lat": 9.6651399, "lon": 5.0829055}, {"type": "node", "id": 3233854213, "lat": 9.667966, "lon": 5.0841255}, {"type": "node", "id": 3233854214, "lat": 9.6723554, "lon": 5.0832105}, {"type": "node", "id": 3233854215, "lat": 9.677767, "lon": 5.0844914}, {"type": "node", "id": 3233854216, "lat": 9.6828779, "lon": 5.0844304}, {"type": "node", "id": 3233854217, "lat": 9.6883562, "lon": 5.0857923, "tags": {"ford": "yes"}}, {"type": "node", "id": 3233854218, "lat": 9.6980296, "lon": 5.0861993}, {"type": "node", "id": 5863898718, "lat": 9.5132601, "lon": 5.0095615}, {"type": "node", "id": 5863898719, "lat": 9.513254, "lon": 5.0101377}, {"type": "node", "id": 5863898720, "lat": 9.5135258, "lon": 5.0104424}, {"type": "node", "id": 5863898721, "lat": 9.5137689, "lon": 5.0105544}, {"type": "node", "id": 5863898722, "lat": 9.5139288, "lon": 5.0105175}, {"type": "node", "id": 5863898723, "lat": 9.514017, "lon": 5.0102603}, {"type": "node", "id": 5863898724, "lat": 9.5140887, "lon": 5.0102142}, {"type": "node", "id": 5863898725, "lat": 9.5144199, "lon": 5.0103861}, {"type": "node", "id": 5863898726, "lat": 9.5146547, "lon": 5.0103406}, {"type": "node", "id": 5863898727, "lat": 9.5147345, "lon": 5.0104055}, {"type": "node", "id": 5863898728, "lat": 9.5147706, "lon": 5.0105343}, {"type": "node", "id": 5863898729, "lat": 9.5147188, "lon": 5.0106357}, {"type": "node", "id": 5863898730, "lat": 9.5147926, "lon": 5.010812}, {"type": "node", "id": 5863898731, "lat": 9.5149313, "lon": 5.0108992}, {"type": "node", "id": 5863898732, "lat": 9.5156175, "lon": 5.0120008}, {"type": "node", "id": 5863898733, "lat": 9.5151904, "lon": 5.0110322}, {"type": "node", "id": 5863898734, "lat": 9.5156914, "lon": 5.0121927}, {"type": "node", "id": 5863898735, "lat": 9.5157319, "lon": 5.0123899}, {"type": "node", "id": 5863898736, "lat": 9.5157263, "lon": 5.0126313}, {"type": "node", "id": 5863898737, "lat": 9.5156013, "lon": 5.012799}, {"type": "node", "id": 5863898738, "lat": 9.5154867, "lon": 5.0130018}, {"type": "node", "id": 5863898739, "lat": 9.5153706, "lon": 5.0131033}, {"type": "node", "id": 5863898740, "lat": 9.5157325, "lon": 5.0133418}, {"type": "node", "id": 5863898741, "lat": 9.5159556, "lon": 5.0133535}, {"type": "node", "id": 5863898742, "lat": 9.5161175, "lon": 5.0134072}, {"type": "node", "id": 5863898743, "lat": 9.5161822, "lon": 5.0133216}, {"type": "node", "id": 5863898744, "lat": 9.5162723, "lon": 5.0132333}, {"type": "node", "id": 5863898745, "lat": 9.5162567, "lon": 5.0130872}, {"type": "node", "id": 5863898746, "lat": 9.5162303, "lon": 5.0129056}, {"type": "node", "id": 5863898747, "lat": 9.5161383, "lon": 5.0127375}, {"type": "node", "id": 5863898748, "lat": 9.5161856, "lon": 5.0126446}, {"type": "node", "id": 5863898749, "lat": 9.5163649, "lon": 5.0125999}, {"type": "node", "id": 5863898750, "lat": 9.5166135, "lon": 5.0126159}, {"type": "node", "id": 5863898751, "lat": 9.5168575, "lon": 5.0127557}, {"type": "node", "id": 5863898752, "lat": 9.5171054, "lon": 5.0129889}, {"type": "node", "id": 5863898753, "lat": 9.517292, "lon": 5.0132253}, {"type": "node", "id": 5863898754, "lat": 9.5172865, "lon": 5.0133166}, {"type": "node", "id": 5863898755, "lat": 9.5172, "lon": 5.0134626}, {"type": "node", "id": 5863898756, "lat": 9.517145, "lon": 5.0135015}, {"type": "node", "id": 5863898757, "lat": 9.5171686, "lon": 5.0136094}, {"type": "node", "id": 5863898758, "lat": 9.5171466, "lon": 5.013727}, {"type": "node", "id": 5863898759, "lat": 9.5171769, "lon": 5.0138432}, {"type": "node", "id": 5863898760, "lat": 9.5173148, "lon": 5.0138559}, {"type": "node", "id": 5863898761, "lat": 9.5174285, "lon": 5.0137229}, {"type": "node", "id": 5863898762, "lat": 9.5176499, "lon": 5.0136038}, {"type": "node", "id": 5863898763, "lat": 9.5178689, "lon": 5.013616}, {"type": "node", "id": 5863898764, "lat": 9.5179953, "lon": 5.013656}, {"type": "node", "id": 5863898765, "lat": 9.5180906, "lon": 5.0138979}, {"type": "node", "id": 5863898766, "lat": 9.518169, "lon": 5.0141348}, {"type": "node", "id": 5863898767, "lat": 9.5182795, "lon": 5.0141942}, {"type": "node", "id": 5863898768, "lat": 9.5183798, "lon": 5.0141906}, {"type": "node", "id": 5863898769, "lat": 9.5186106, "lon": 5.0141331}, {"type": "node", "id": 5863898770, "lat": 9.5186872, "lon": 5.0142261}, {"type": "node", "id": 5863898771, "lat": 9.518706, "lon": 5.0143205}, {"type": "node", "id": 5863898772, "lat": 9.5186674, "lon": 5.0143788}, {"type": "node", "id": 5863898773, "lat": 9.518578, "lon": 5.0144015}, {"type": "node", "id": 5863898774, "lat": 9.5184213, "lon": 5.0143907}, {"type": "node", "id": 5863898775, "lat": 9.518322, "lon": 5.0143578}, {"type": "node", "id": 5863898776, "lat": 9.5182028, "lon": 5.0144081}, {"type": "node", "id": 5863898777, "lat": 9.5181224, "lon": 5.014521}, {"type": "node", "id": 5863898778, "lat": 9.5180874, "lon": 5.0146784}, {"type": "node", "id": 5863898779, "lat": 9.518138, "lon": 5.0148466}, {"type": "node", "id": 5863898780, "lat": 9.5181742, "lon": 5.0150095}, {"type": "node", "id": 5863898781, "lat": 9.5181814, "lon": 5.0151471}, {"type": "node", "id": 5863898782, "lat": 9.5182042, "lon": 5.0152972}, {"type": "node", "id": 5863898783, "lat": 9.5182087, "lon": 5.0154801}, {"type": "node", "id": 5863898784, "lat": 9.5182523, "lon": 5.0156342}, {"type": "node", "id": 5863898785, "lat": 9.518321, "lon": 5.0157788}, {"type": "node", "id": 5863898786, "lat": 9.5185079, "lon": 5.0159238}, {"type": "node", "id": 5863898787, "lat": 9.5186702, "lon": 5.0160772}, {"type": "node", "id": 5863898788, "lat": 9.5187023, "lon": 5.0161617}, {"type": "node", "id": 5863898789, "lat": 9.5186956, "lon": 5.0162384}, {"type": "node", "id": 5863898790, "lat": 9.5186739, "lon": 5.016353}, {"type": "node", "id": 5863898791, "lat": 9.5186856, "lon": 5.0165323}, {"type": "node", "id": 5863898792, "lat": 9.5186836, "lon": 5.0166921}, {"type": "node", "id": 5863935936, "lat": 9.5155695, "lon": 5.0119088}, {"type": "node", "id": 5863935937, "lat": 9.5154615, "lon": 5.0118843}, {"type": "node", "id": 5863935938, "lat": 9.5153441, "lon": 5.0118692}, {"type": "node", "id": 5863935939, "lat": 9.5152975, "lon": 5.0116803}, {"type": "node", "id": 5863935940, "lat": 9.5152025, "lon": 5.0116614}, {"type": "node", "id": 5863935941, "lat": 9.5150517, "lon": 5.0115443}, {"type": "node", "id": 5863935942, "lat": 9.5149809, "lon": 5.011482}, {"type": "node", "id": 5863935943, "lat": 9.5148952, "lon": 5.0114008}, {"type": "node", "id": 5863935944, "lat": 9.5148095, "lon": 5.0113403}, {"type": "node", "id": 5863935945, "lat": 9.5147555, "lon": 5.0113158}, {"type": "node", "id": 5863935946, "lat": 9.5147368, "lon": 5.0112194}, {"type": "node", "id": 5863935947, "lat": 9.5146772, "lon": 5.0111873}, {"type": "node", "id": 5863935948, "lat": 9.5146493, "lon": 5.011074}, {"type": "node", "id": 5863935949, "lat": 9.5145655, "lon": 5.0110362}, {"type": "node", "id": 5863935950, "lat": 9.5145208, "lon": 5.0109711}, {"type": "node", "id": 5863935951, "lat": 9.5145021, "lon": 5.0108917}, {"type": "node", "id": 5863935952, "lat": 9.5144826, "lon": 5.0108351}, {"type": "node", "id": 5863935953, "lat": 9.5144211, "lon": 5.0107888}, {"type": "node", "id": 5863935954, "lat": 9.5143494, "lon": 5.0107463}, {"type": "node", "id": 5863935955, "lat": 9.5142525, "lon": 5.010735}, {"type": "node", "id": 5863935956, "lat": 9.5141063, "lon": 5.0106802}, {"type": "node", "id": 5863935957, "lat": 9.5139638, "lon": 5.0105593}, {"type": "node", "id": 5863935958, "lat": 9.5139119, "lon": 5.0105214}, {"type": "node", "id": 5863999886, "lat": 9.5152745, "lon": 5.0111033}, {"type": "node", "id": 5863999887, "lat": 9.5153372, "lon": 5.0112016}, {"type": "node", "id": 5863999888, "lat": 9.5153429, "lon": 5.0112941}, {"type": "node", "id": 5863999889, "lat": 9.5153458, "lon": 5.0114127}, {"type": "node", "id": 5863999890, "lat": 9.5152831, "lon": 5.0114705}, {"type": "node", "id": 5863999891, "lat": 9.5153857, "lon": 5.0115399}, {"type": "node", "id": 5863999892, "lat": 9.5154656, "lon": 5.0115977}, {"type": "node", "id": 5863999893, "lat": 9.5155083, "lon": 5.0116874}, {"type": "node", "id": 5863999894, "lat": 9.5155169, "lon": 5.0117972}, {"type": "node", "id": 5863999895, "lat": 9.5155242, "lon": 5.0118985}, {"type": "node", "id": 5863999896, "lat": 9.5132542, "lon": 5.0099322}, {"type": "node", "id": 5863999897, "lat": 9.5132542, "lon": 5.0099322}, {"type": "node", "id": 5863999898, "lat": 9.513187, "lon": 5.0098888}, {"type": "node", "id": 5863999899, "lat": 9.51313, "lon": 5.0098744}, {"type": "node", "id": 5863999900, "lat": 9.5130672, "lon": 5.0098454}, {"type": "node", "id": 5863999901, "lat": 9.513033, "lon": 5.009776}, {"type": "node", "id": 6007714669, "lat": 9.5523845, "lon": 5.1417443}, {"type": "node", "id": 6011470615, "lat": 9.5789132, "lon": 5.1750837}, {"type": "node", "id": 6011470616, "lat": 9.5784931, "lon": 5.1748957}, {"type": "node", "id": 6011470617, "lat": 9.5781893, "lon": 5.1745506}, {"type": "node", "id": 6011470618, "lat": 9.5782014, "lon": 5.17407}, {"type": "node", "id": 6011470619, "lat": 9.5779705, "lon": 5.1736509}, {"type": "node", "id": 6011470620, "lat": 9.5779098, "lon": 5.1729361}, {"type": "node", "id": 6011470621, "lat": 9.5778733, "lon": 5.1724925}, {"type": "node", "id": 6011470622, "lat": 9.5777275, "lon": 5.1719872}, {"type": "node", "id": 6011470623, "lat": 9.57729, "lon": 5.1714819}, {"type": "node", "id": 6011470624, "lat": 9.5774115, "lon": 5.1709396}, {"type": "node", "id": 6011470625, "lat": 9.5774115, "lon": 5.1706438}, {"type": "node", "id": 6011470626, "lat": 9.5770469, "lon": 5.1702741}, {"type": "node", "id": 6011470627, "lat": 9.5769376, "lon": 5.1698304}, {"type": "node", "id": 6011470628, "lat": 9.5765122, "lon": 5.16951}, {"type": "node", "id": 6011470629, "lat": 9.5764515, "lon": 5.1688199}, {"type": "node", "id": 6011470630, "lat": 9.576415, "lon": 5.1686103}, {"type": "node", "id": 6011470631, "lat": 9.5756737, "lon": 5.1686103}, {"type": "node", "id": 6011470632, "lat": 9.5754185, "lon": 5.1686103}, {"type": "node", "id": 6011470633, "lat": 9.5752848, "lon": 5.1680804}, {"type": "node", "id": 6011470634, "lat": 9.5746407, "lon": 5.1680927}, {"type": "node", "id": 6285565739, "lat": 9.398957, "lon": 4.8497557}, {"type": "node", "id": 6285565740, "lat": 9.3959721, "lon": 4.8452496}, {"type": "node", "id": 6285565741, "lat": 9.3934451, "lon": 4.8378468}, {"type": "node", "id": 7096401175, "lat": 9.4608196, "lon": 4.9642056}, {"type": "node", "id": 7096401176, "lat": 9.4601159, "lon": 4.9642056}, {"type": "node", "id": 7096401177, "lat": 9.4591105, "lon": 4.964624}, {"type": "node", "id": 7096401178, "lat": 9.4619838, "lon": 4.9656004}, {"type": "node", "id": 7876299184, "lat": 9.6912968, "lon": 5.0858986, "tags": {"ford": "yes"}}, {"type": "node", "id": 8178378090, "lat": 9.5712665, "lon": 5.0712809}, {"type": "node", "id": 8541270272, "lat": 9.4209885, "lon": 4.8732133}, {"type": "way", "id": 317146025, "nodes": [6011470634, 3233854104, 3233854097, 3233854092, 6007714669, 3233854090, 3233854078, 3233854072, 3233854064, 3233854069, 3233854066, 3233854067, 3233854075, 3233854083, 3233854085, 3233854091], "tags": {"waterway": "stream"}}, {"type": "way", "id": 317146026, "nodes": [3233854218, 7876299184, 3233854217, 3233854216, 3233854215, 3233854214, 3233854213, 3233854212, 3233854200, 3233854197, 3233854192, 3233854191, 3233854187, 3233854183, 3233854179, 3233854164, 3233854151, 3233854133, 3233854129, 3233854118, 3233854114, 3233854106, 8178378090, 3233854098, 3233854095, 3233854094, 3233854091], "tags": {"waterway": "stream"}}, {"type": "way", "id": 317146029, "nodes": [3233854091, 3233854088, 3233854084, 3233854081, 3233854079, 3233854077, 3233854074, 3233854073, 3233854063, 3233854065, 3233854062, 3233854061, 3233854059, 3233854057, 5863898792, 5863898791, 5863898790, 5863898789, 5863898788, 5863898787, 5863898786, 5863898785, 5863898784, 5863898783, 5863898782, 5863898781, 5863898780, 5863898779, 5863898778, 5863898777, 5863898776, 5863898775, 5863898774, 5863898773, 5863898772, 5863898771, 5863898770, 5863898769, 5863898768, 5863898767, 5863898766, 5863898765, 5863898764, 5863898763, 5863898762, 5863898761, 5863898760, 5863898759, 5863898758, 5863898757, 5863898756, 5863898755, 5863898754, 5863898753, 5863898752, 5863898751, 5863898750, 5863898749, 5863898748, 5863898747, 5863898746, 5863898745, 5863898744, 5863898743, 5863898742, 5863898741, 5863898740, 5863898739, 5863898738, 5863898737, 5863898736, 5863898735, 5863898734, 5863898732, 5863935936, 5863999895, 5863935937, 5863935938, 5863935939, 5863935940, 5863935941, 5863935942, 5863935943, 5863935944, 5863935945, 5863935946, 5863935947, 5863935948, 5863935949, 5863935950, 5863935951, 5863935952, 5863935953, 5863935954, 5863935955, 5863935956, 5863935957, 5863935958], "tags": {"waterway": "river"}}, {"type": "way", "id": 620671777, "nodes": [5863898718, 3233854052, 3233854051, 3233854049, 3233854048, 3233854045, 3233854042, 3233854041, 3233854040, 3233854038, 3233854037, 3233854036, 3233854035, 3233854034, 3233854033, 3233854031, 3233854027, 3233854010, 3233854004, 7096401178, 7096401175, 7096401176, 7096401177, 3233853967, 3233853964, 3233853963, 3233853961, 3233853960, 3233853958, 3233853959, 3233853957, 3233853956, 8541270272, 3233853955, 3233853954, 6285565739, 6285565740, 3233853953, 3233853952, 6285565741], "tags": {"waterway": "river"}}, {"type": "way", "id": 620671778, "nodes": [5863999895, 5863999894, 5863999893, 5863999892, 5863999891, 5863999890, 5863999889, 5863999888, 5863999887, 5863999886, 5863898733, 5863898731, 5863898730, 5863898729, 5863898728, 5863898727, 5863898726, 5863898725, 5863898724, 5863898723, 5863898722, 5863935958, 5863898721, 5863898720, 5863898719, 5863999897], "tags": {"waterway": "river"}}, {"type": "way", "id": 620682801, "nodes": [5863999896, 3233854053], "tags": {"waterway": "river"}}, {"type": "way", "id": 620682802, "nodes": [5863999897, 5863999898, 5863999899, 5863999900, 5863999901], "tags": {"waterway": "river"}}, {"type": "way", "id": 637682437, "nodes": [6011470615, 6011470616, 6011470617, 6011470618, 6011470619, 6011470620, 6011470621, 6011470622, 6011470623, 6011470624, 6011470625, 6011470626, 6011470627, 6011470628, 6011470629, 6011470630, 6011470631, 6011470632, 6011470633, 6011470634], "tags": {"waterway": "stream"}}, {"type": "way", "id": 916243508, "nodes": [3233854131, 3233854123, 3233854122, 3233854110, 3233854113, 3233854103, 3233854101, 3233854115, 3233854120, 6011470615], "tags": {"waterway": "stream"}}]}