{"version": 0.6, "generator": "Overpass API 0.7.62.4 2390de5a", "osm3s": {"timestamp_osm_base": "2024-11-23T15:41:56Z", "copyright": "The data included in this document is from www.openstreetmap.org. The data is made available under ODbL."}, "elements": [{"type": "node", "id": 7916720384, "lat": 7.9895802, "lon": 5.1920389}, {"type": "node", "id": 7916728385, "lat": 7.9895397, "lon": 5.1920709}, {"type": "node", "id": 7916728386, "lat": 7.9892838, "lon": 5.1917397}, {"type": "node", "id": 7916728387, "lat": 7.9893243, "lon": 5.1917077}, {"type": "way", "id": 848399712, "nodes": [7916728387, 7916728386, 7916728385, 7916720384, 7916728387], "tags": {"waterway": "dam"}}]}